string_tools/__init__.py
string_tools/main.py
string_tools/string_ops.py
keita_string_tools-0.1.0.dist-info/METADATA
keita_string_tools-0.1.0.dist-info/WHEEL
keita_string_tools-0.1.0.dist-info/RECORD
