Metadata-Version: 2.4
Name: keita-string-tools
Version: 0.1.0
Summary: 
Author: keita223
Author-email: mamadikeita717@gmail.com
Requires-Python: >=3.12
Classifier: Programming Language :: Python :: 3
Classifier: Programming Language :: Python :: 3.12
Classifier: Programming Language :: Python :: 3.13
Classifier: Programming Language :: Python :: 3.14
